pycode_similar.py
pycode_similar-1.4.dist-info/LICENSE
pycode_similar-1.4.dist-info/METADATA
pycode_similar-1.4.dist-info/WHEEL
pycode_similar-1.4.dist-info/entry_points.txt
pycode_similar-1.4.dist-info/top_level.txt
pycode_similar-1.4.dist-info/RECORD
