Metadata-Version: 2.1
Name: pycode-similar
Version: 1.4
Summary: A simple plagiarism detection tool for python code
Home-page: https://github.com/fyrestone/pycode_similar
Author: fyrestone
Author-email: fyrestone@outlook.com
License: MIT License
Keywords: code similarity plagiarism moss generic utility
Platform: All
Classifier: Development Status :: 5 - Production/Stable
Classifier: Intended Audience :: Developers
Classifier: License :: OSI Approved :: MIT License
Classifier: Natural Language :: English
Classifier: Operating System :: OS Independent
Classifier: Programming Language :: Python :: 2
Classifier: Programming Language :: Python :: 3
Classifier: Topic :: Software Development :: Libraries
Classifier: Topic :: Utilities
